datasetcrux/__init__.py
datasetcrux/csvfun.py
datasetcrux/datasetcrux.py
datasetcrux/ranfun.py
datasetcrux-0.0.33.dist-info/LICENSE
datasetcrux-0.0.33.dist-info/METADATA
datasetcrux-0.0.33.dist-info/WHEEL
datasetcrux-0.0.33.dist-info/top_level.txt
datasetcrux-0.0.33.dist-info/RECORD
