Metadata-Version: 2.1
Name: datasetcrux
Version: 0.0.33
Summary: Dataset creation, management and analysis tool
Home-page: https://github.com/datasetcrux/datasetcrux
Author: Vinay Panchal
Author-email: vinay.npanchal@gmail.com
License: UNKNOWN
Project-URL: Bug Tracker, https://github.com/datasetcrux/datasetcrux/issues
Platform: UNKNOWN
Classifier: Programming Language :: Python :: 3
Classifier: License :: OSI Approved :: MIT License
Classifier: Operating System :: Microsoft :: Windows 
Classifier: Operating System :: POSIX
Classifier: Operating System :: Unix
Classifier: Operating System :: MacOS
Classifier: Operating System :: OS Independent
Requires-Python: >=3.6
License-File: LICENSE
